{
  "EN": {
    "language": "English",
    "chat_tab": "Chat",
    "settings_tab": "Settings",
    "language_title": "Language",
    "language_hint": "Choose your preferred language.",
    "appearance_title": "Appearance",
    "appearance_hint": "Choose your preferred style.",
    "theme_default": "Default (Dark)",
    "theme_light": "Light",
    "theme_feminine": "Elegant",
    "login": "Login",
    "logout": "Logout",
    "checking": "Checking…",
    "Type_a_message": "Type a message...",
    "Send": "Send",
    "tips_send": "Press Enter to send • Shift+Enter for new line",
    "good_morning": "Good morning",
    "good_afternoon": "Good afternoon",
    "good_evening": "Good evening",
    "good_night": "Good night",
    "greeting_user": "{greeting}, {name}. How may I serve you today?",
    "greeting_casual": "{greeting}, momo. how is the hippo?",
    "greeting_formal": "{greeting}, Your Sovereign Majesty. How may I be of service?",
    "greeting_guest": "{greeting}, Your grace. I'm Moo-AI. How may I serve you today?",

    "EN_native": "English",
    "PT_native": "Português",
    "ES_native": "Español",
    "DE_native": "Deutsch",
    "FR_native": "Français",
    "GE_native": "ქართული",
    "RU_native": "Русский"
  },

  "PT": {
    "language": "Português",
    "chat_tab": "Chat",
    "settings_tab": "Configurações",
    "language_title": "Idioma",
    "language_hint": "Escolha seu idioma preferido.",
    "appearance_title": "Aparência",
    "appearance_hint": "Escolha seu estilo preferido.",
    "theme_default": "Padrão (Escuro)",
    "theme_light": "Claro",
    "theme_feminine": "Elegante",
    "login": "Entrar",
    "logout": "Sair",
    "checking": "Verificando…",
    "Type_a_message": "Digite uma mensagem...",
    "Send": "Enviar",
    "tips_send": "Pressione Enter para enviar • Shift+Enter para nova linha",
    "good_morning": "Bom dia",
    "good_afternoon": "Boa tarde",
    "good_evening": "Boa noite",
    "good_night": "Boa noite",
    "greeting_user": "{greeting}, {name}. Como posso ajudar hoje?",
    "greeting_casual": "{greeting}, momo. como vai o hipopótamo?",
    "greeting_formal": "{greeting}, Sua Majestade Suprema. Como posso ser útil?",
    "greeting_guest": "{greeting}. Eu sou a Moo-AI. Como posso ajudar hoje?",

    "EN_native": "English",
    "PT_native": "Português",
    "ES_native": "Español",
    "DE_native": "Deutsch",
    "FR_native": "Français",
    "GE_native": "ქართული",
    "RU_native": "Русский"
  },

  "FR": {
    "language": "Français",
    "chat_tab": "Chat",
    "settings_tab": "Réglages",
    "language_title": "Langue",
    "language_hint": "Choisissez votre langue préférée.",
    "appearance_title": "Apparence",
    "appearance_hint": "Choisissez votre style préféré.",
    "theme_default": "Par défaut (Sombre)",
    "theme_light": "Clair",
    "theme_feminine": "Élégant",
    "login": "Connexion",
    "logout": "Déconnexion",
    "checking": "Vérification…",
    "Type_a_message": "Tapez un message...",
    "Send": "Envoyer",
    "tips_send": "Appuyez sur Entrée pour envoyer • Maj+Entrée pour une nouvelle ligne",
    "good_morning": "Bonjour",
    "good_afternoon": "Bon après-midi",
    "good_evening": "Bonsoir",
    "good_night": "Bonne nuit",
    "greeting_user": "{greeting}, {name}. Comment puis-je vous aider aujourd'hui ?",
    "greeting_casual": "{greeting}, momo. comment va l'hippopotame ?",
    "greeting_formal": "{greeting}, Votre Majesté Souveraine. Comment puis-je vous être utile ?",
    "greeting_guest": "{greeting}. Je suis Moo-AI. Comment puis-je vous aider aujourd'hui ?",

    "EN_native": "English",
    "PT_native": "Português",
    "ES_native": "Español",
    "DE_native": "Deutsch",
    "FR_native": "Français",
    "GE_native": "ქართული",
    "RU_native": "Русский"
  },

  "DE": {
    "language": "Deutsch",
    "chat_tab": "Chat",
    "settings_tab": "Einstellungen",
    "language_title": "Sprache",
    "language_hint": "Wähle deine bevorzugte Sprache.",
    "appearance_title": "Erscheinungsbild",
    "appearance_hint": "Wähle deinen bevorzugten Stil.",
    "theme_default": "Standard (Dunkel)",
    "theme_light": "Hell",
    "theme_feminine": "Elegant",
    "login": "Anmelden",
    "logout": "Abmelden",
    "checking": "Wird geprüft…",
    "Type_a_message": "Nachricht eingeben...",
    "Send": "Senden",
    "tips_send": "Enter zum Senden • Shift+Enter für neue Zeile",
    "good_morning": "Guten Morgen",
    "good_afternoon": "Guten Tag",
    "good_evening": "Guten Abend",
    "good_night": "Gute Nacht",
    "greeting_user": "{greeting}, {name}. Wie kann ich dir heute helfen?",
    "greeting_casual": "{greeting}, Momo. wie geht es dem Nilpferd?",
    "greeting_formal": "{greeting}, Eure Souveräne Majestät. Wie darf ich dienen?",
    "greeting_guest": "{greeting}. Ich bin Moo-AI. Wie kann ich heute helfen?",

    "EN_native": "English",
    "PT_native": "Português",
    "ES_native": "Español",
    "DE_native": "Deutsch",
    "FR_native": "Français",
    "GE_native": "ქართული",
    "RU_native": "Русский"
  },

  "ES": {
    "language": "Español",
    "chat_tab": "Chat",
    "settings_tab": "Ajustes",
    "language_title": "Idioma",
    "language_hint": "Elige tu idioma preferido.",
    "appearance_title": "Apariencia",
    "appearance_hint": "Elige tu estilo preferido.",
    "theme_default": "Predeterminado (Oscuro)",
    "theme_light": "Claro",
    "theme_feminine": "Elegante",
    "login": "Iniciar sesión",
    "logout": "Cerrar sesión",
    "checking": "Comprobando…",
    "Type_a_message": "Escribe un mensaje...",
    "Send": "Enviar",
    "tips_send": "Pulsa Enter para enviar • Shift+Enter para nueva línea",
    "good_morning": "Buenos días",
    "good_afternoon": "Buenas tardes",
    "good_evening": "Buenas noches",
    "good_night": "Buenas noches",
    "greeting_user": "{greeting}, {name}. ¿Cómo puedo ayudarte hoy?",
    "greeting_casual": "{greeting}, momo. ¿cómo está el hipopótamo?",
    "greeting_formal": "{greeting}, Su Majestad Soberana. ¿En qué puedo servirle?",
    "greeting_guest": "{greeting}. Soy Moo-AI. ¿Cómo puedo ayudarte hoy?",

    "EN_native": "English",
    "PT_native": "Português",
    "ES_native": "Español",
    "DE_native": "Deutsch",
    "FR_native": "Français",
    "GE_native": "ქართული",
    "RU_native": "Русский"
  },

  "GE": {
    "language": "ქართული",
    "chat_tab": "ჩეთი",
    "settings_tab": "პარამეტრები",
    "language_title": "ენა",
    "language_hint": "აირჩიეთ სასურველი ენა.",
    "appearance_title": "გარეგნობა",
    "appearance_hint": "აირჩიეთ სასურველი სტილი.",
    "theme_default": "ნაგულისხმევი (მუქი)",
    "theme_light": "ღია",
    "theme_feminine": "ელეგანტური",
    "login": "შესვლა",
    "logout": "გასვლა",
    "checking": "შემოწმება…",
    "Type_a_message": "დაწერეთ შეტყობინება...",
    "Send": "გაგზავნა",
    "tips_send": "Enter — გაგზავნა • Shift+Enter — ახალი ხაზი",
    "good_morning": "დილა მშვიდობისა",
    "good_afternoon": "შუადღე მშვიდობისა",
    "good_evening": "საღამო მშვიდობისა",
    "good_night": "ღამე მშვიდობისა",
    "greeting_user": "{greeting}, {name}. როგორ დაგეხმაროთ დღეს?",
    "greeting_casual": "{greeting}, მომო. როგორ არის ჰიპოპოტამი?",
    "greeting_formal": "{greeting}, თქვენი სუვერენული უდიდებულესობა. როგორ შემიძლია გემსახუროთ?",
    "greeting_guest": "{greeting}. მე ვარ Moo-AI. როგორ დაგეხმაროთ დღეს?",

    "EN_native": "English",
    "PT_native": "Português",
    "ES_native": "Español",
    "DE_native": "Deutsch",
    "FR_native": "Français",
    "GE_native": "ქართული",
    "RU_native": "Русский"
  },

  "RU": {
    "language": "Русский",
    "chat_tab": "Чат",
    "settings_tab": "Настройки",
    "language_title": "Язык",
    "language_hint": "Выберите предпочитаемый язык.",
    "appearance_title": "Оформление",
    "appearance_hint": "Выберите предпочитаемый стиль.",
    "theme_default": "По умолчанию (тёмная)",
    "theme_light": "Светлая",
    "theme_feminine": "Элегантная",
    "login": "Войти",
    "logout": "Выйти",
    "checking": "Проверка…",
    "Type_a_message": "Введите сообщение...",
    "Send": "Отправить",
    "tips_send": "Enter — отправить • Shift+Enter — новая строка",
    "good_morning": "Доброе утро",
    "good_afternoon": "Добрый день",
    "good_evening": "Добрый вечер",
    "good_night": "Спокойной ночи",
    "greeting_user": "{greeting}, {name}. Чем я могу помочь сегодня?",
    "greeting_casual": "{greeting}, момо. как там бегемотик?",
    "greeting_formal": "{greeting}, Ваше Суверенное Величество. Чем я могу служить?",
    "greeting_guest": "{greeting}. Я Moo-AI. Чем я могу помочь сегодня?",

    "EN_native": "English",
    "PT_native": "Português",
    "ES_native": "Español",
    "DE_native": "Deutsch",
    "FR_native": "Français",
    "GE_native": "ქართული",
    "RU_native": "Русский"
  }
}
